MANIFEST.in
README.md
setup.cfg
setup.py
examples/microservice_decorator_input.py
examples/microservice_stream_input.py
examples/requirements.txt
tamarco_kafka/__init__.py
tamarco_kafka/connection.py
tamarco_kafka/exceptions.py
tamarco_kafka/helpers.py
tamarco_kafka/input.py
tamarco_kafka/output.py
tamarco_kafka/resource.py
tamarco_kafka/settings.py
tamarco_kafka.egg-info/PKG-INFO
tamarco_kafka.egg-info/SOURCES.txt
tamarco_kafka.egg-info/dependency_links.txt
tamarco_kafka.egg-info/not-zip-safe
tamarco_kafka.egg-info/requires.txt
tamarco_kafka.egg-info/top_level.txt
tests/__init__.py
tests/bootstrap-librdkafka.sh
tests/utils.py
tests/functional/__init__.py
tests/functional/conftest.py
tests/functional/test_connection.py
tests/functional/test_input.py
tests/functional/test_output.py
tests/functional/test_resource.py
tests/unit/__init__.py
tests/unit/test_input.py
tests/unit/test_resource.py