Metadata-Version: 2.1
Name: tamarco-kafka
Version: 0.1.0
Summary: Kafka resource for Tamarco microservice framework.
Home-page: https://github.com/System73/tamarco-kafka
Author: System73 Engineering Team
Author-email: opensource@system73.com
License: UNKNOWN
Keywords: tamarco,kafka,microservices
Platform: UNKNOWN
Classifier: Development Status :: 4 - Beta
Classifier: License :: OSI Approved :: MIT License
Classifier: Intended Audience :: Developers
Classifier: Natural Language :: English
Classifier: Programming Language :: Python :: 3.6
